djangorestframework_link_header_pagination-0.1.1.dist-info/DESCRIPTION.rst
djangorestframework_link_header_pagination-0.1.1.dist-info/METADATA
djangorestframework_link_header_pagination-0.1.1.dist-info/RECORD
djangorestframework_link_header_pagination-0.1.1.dist-info/WHEEL
djangorestframework_link_header_pagination-0.1.1.dist-info/metadata.json
djangorestframework_link_header_pagination-0.1.1.dist-info/top_level.txt
drf_link_header_pagination/__init__.py
